.coveragerc
.travis.yml
AUTHORS
ChangeLog
LICENSE
MANIFEST.in
README.rst
requirements.txt
setup.cfg
setup.py
tox.ini
django_service_templates/__init__.py
django_service_templates/admin.py
django_service_templates/engine.py
django_service_templates/models.py
django_service_templates/settings.py
django_service_templates/signals.py
django_service_templates/urls.py
django_service_templates/views.py
django_service_templates.egg-info/PKG-INFO
django_service_templates.egg-info/SOURCES.txt
django_service_templates.egg-info/dependency_links.txt
django_service_templates.egg-info/not-zip-safe
django_service_templates.egg-info/pbr.json
django_service_templates.egg-info/requires.txt
django_service_templates.egg-info/top_level.txt
django_service_templates/migrations/0001_initial.py
django_service_templates/migrations/0002_auto_20151126_2136.py
django_service_templates/migrations/__init__.py
django_service_templates/templates/admin/change_form_with_render_button.html
docs/Makefile
docs/make.bat
docs/source/conf.py
docs/source/index.rst
docs/source/readme.rst
requirements/default.txt
requirements/tests.txt
tests/cov.sh
tests/local_settings.py
tests/manage.py
tests/testapp/__init__.py
tests/testapp/models.py
tests/testapp/settings.py
tests/testapp/urls.py
tests/testapp/tests/__init__.py
tests/testapp/tests/test_commands.py